qcheck/__init__.py
qcheck/main.py
qchk-0.0.1.dist-info/METADATA
qchk-0.0.1.dist-info/WHEEL
qchk-0.0.1.dist-info/entry_points.txt
qchk-0.0.1.dist-info/top_level.txt
qchk-0.0.1.dist-info/RECORD
