Metadata-Version: 2.1
Name: qchk
Version: 0.0.1
Summary: A python package to display quota info
Home-page: https://github.com/gruunday/qcheck
Author: Tom Doyle
Author-email: gruunday@gmail.com
Project-URL: Bug Tracker, https://github.com/gruunday/qcheck/issues
Classifier: Programming Language :: Python :: 3
Classifier: License :: OSI Approved :: MIT License
Requires-Python: >=3.6
